Metadata-Version: 2.1
Name: pybind11-cuda-array-interface
Version: 1.0.0
Summary: pybind11 headers supporting the __cuda_array_interface__
Author-email: Mikael Twengström <m.twengstrom@gmail.com>
License: Copyright (c) 2021, Mikael Twengström
Project-URL: repository, https://github.com/mikaeltw/pybind11_cuda_array_interface
Classifier: Programming Language :: C++
Classifier: Programming Language :: Python :: 3 :: Only
Classifier: Programming Language :: Python :: 3.8
Classifier: Programming Language :: Python :: 3.9
Classifier: Programming Language :: Python :: 3.10
Classifier: Programming Language :: Python :: 3.11
Classifier: License :: OSI Approved :: BSD License
Requires-Python: >=3.8
Provides-Extra: test
License-File: LICENSE
